{
  "schema": {
    "mealid": "套餐id",
    "i": "组件唯一标识",
    "x": "坐标X",
    "y": "坐标Y",
    "w": "宽",
    "h": "高",
    "minw": "最小宽",
    "maxw": "最大宽",
    "still": "是否固定位置",
    "path": "源码路径",
    "imgurl": "图片路径",
    "moduletype": "组件类型",
    "title": "标题",
    "style": "样式",
    "id": "id",
    "mountid": "mountId",
    "showtitle": "显示",
    "showdetail": "显示详情",
    "detailpath": "详情路径"
  },
  "data": [
    {
      "mealid": 89,
      "i": "sq10",
      "x": 0,
      "y": 0,
      "w": 12,
      "h": 12,
      "minw": 0,
      "maxw": 0,
      "still": false,
      "path": "../../thirdModules/szy/lib/main/index.js",
      "imgurl": "http://47.95.1.229:9003/UploadFile/201808/szy.png",
      "title": "水资源",
      "style": "{}",
      "id": 117,
      "showdetail": true,
      "detailpath": "http://10.17.200.212/zjszy/indexReal-3.0.jsp"
    },
    {
      "mealid": 89,
      "i": "sq11",
      "x": 0,
      "y": 12,
      "w": 3,
      "h": 9,
      "minw": 0,
      "maxw": 0,
      "still": false,
      "path": "../../thirdModules/dzx/lib/main/index.js",
      "imgurl": "http://47.95.1.229:9003/UploadFile/201808/dzx.png",
      "title": "水雨情",
      "style": "{}",
      "id": 118,
      "showdetail": true,
      "detailpath": "http://www.htwater.net:48080/zjfx/index.html"
    },
    {
      "mealid": 89,
      "i": "sq12",
      "x": 3,
      "y": 12,
      "w": 3,
      "h": 9,
      "minw": 0,
      "maxw": 0,
      "still": false,
      "path": "../../thirdModules/gcjs/lib/main/index.js",
      "imgurl": "http://47.95.1.229:9003/UploadFile/201808/工程建设.jpg",
      "title": "工程建设",
      "style": "{}",
      "id": 119,
      "showdetail": true,
      "detailpath": "http://112.124.46.96:8080/#/supervision/indexPrime"
    },
    {
      "mealid": 89,
      "i": "sq13",
      "x": 7,
      "y": 12,
      "w": 6,
      "h": 9,
      "minw": 0,
      "maxw": 0,
      "still": false,
      "path": "../../thirdModules/gcyx/lib/main/index.js",
      "imgurl": "http://47.95.1.229:9003/UploadFile/201808/工程运行.jpg",
      "title": "工程运行",
      "style": "{}",
      "id": 120,
      "showdetail": true,
      "detailpath": "http://zjslbzhjg.dcyun.com:49001/bigscreen/index.html#/app/indexPage"
    }
  ],
  "paging": null
}
